odoo/addons/stock_picking_product_interchangeable/README.rst
odoo/addons/stock_picking_product_interchangeable/__init__.py
odoo/addons/stock_picking_product_interchangeable/__manifest__.py
odoo/addons/stock_picking_product_interchangeable/demo/product_demo.xml
odoo/addons/stock_picking_product_interchangeable/demo/stock_demo.xml
odoo/addons/stock_picking_product_interchangeable/i18n/es.po
odoo/addons/stock_picking_product_interchangeable/i18n/it.po
odoo/addons/stock_picking_product_interchangeable/i18n/stock_picking_product_interchangeable.pot
odoo/addons/stock_picking_product_interchangeable/models/__init__.py
odoo/addons/stock_picking_product_interchangeable/models/product.py
odoo/addons/stock_picking_product_interchangeable/models/stock_move.py
odoo/addons/stock_picking_product_interchangeable/models/stock_picking.py
odoo/addons/stock_picking_product_interchangeable/models/stock_picking_type.py
odoo/addons/stock_picking_product_interchangeable/readme/CONFIGURE.md
odoo/addons/stock_picking_product_interchangeable/readme/CONTEXT.md
odoo/addons/stock_picking_product_interchangeable/readme/CONTRIBUTORS.md
odoo/addons/stock_picking_product_interchangeable/readme/DESCRIPTION.md
odoo/addons/stock_picking_product_interchangeable/readme/ROADMAP.md
odoo/addons/stock_picking_product_interchangeable/readme/USAGE.md
odoo/addons/stock_picking_product_interchangeable/static/description/banner.png
odoo/addons/stock_picking_product_interchangeable/static/description/icon.png
odoo/addons/stock_picking_product_interchangeable/static/description/index.html
odoo/addons/stock_picking_product_interchangeable/static/img/new_quotation.png
odoo/addons/stock_picking_product_interchangeable/static/img/op_type_setting.png
odoo/addons/stock_picking_product_interchangeable/static/img/picking_with_substitutes.png
odoo/addons/stock_picking_product_interchangeable/static/img/product_form.png
odoo/addons/stock_picking_product_interchangeable/static/img/product_qty.png
odoo_addon_stock_picking_product_interchangeable-16.0.1.0.0.11.dist-info/METADATA
odoo_addon_stock_picking_product_interchangeable-16.0.1.0.0.11.dist-info/WHEEL
odoo_addon_stock_picking_product_interchangeable-16.0.1.0.0.11.dist-info/top_level.txt
odoo_addon_stock_picking_product_interchangeable-16.0.1.0.0.11.dist-info/RECORD
